Metadata-Version: 1.1
Name: lazy-logger
Version: 0.1.1
Summary: provide a better logging
Home-page: https://github.com/Python-Logging-For-Human/ezlogging
Author: lazy_logger
Author-email: tim.yellow@gmail.com
License: MIT
Platform: any
Classifier: Development Status :: 5 - Production/Stable
Classifier: Environment :: Console
Classifier: Intended Audience :: Developers
Classifier: License :: OSI Approved :: MIT License
Classifier: Operating System :: OS Independent
Classifier: Programming Language :: Python
Classifier: Topic :: Utilities
Classifier: Topic :: Software Development :: Libraries :: Python Modules
